num2al/__init__.py
num2al/num2al.py
num2al-1.1.dist-info/METADATA
num2al-1.1.dist-info/WHEEL
num2al-1.1.dist-info/entry_points.txt
num2al-1.1.dist-info/top_level.txt
num2al-1.1.dist-info/RECORD
