Metadata-Version: 2.1
Name: num2al
Version: 1.1
Summary: A package for converting numbers to Albanian words
